LICENSE
README.md
setup.py
yuankong_test/__init__.py
yuankong_test/main.py
yuankong_test.egg-info/PKG-INFO
yuankong_test.egg-info/SOURCES.txt
yuankong_test.egg-info/dependency_links.txt
yuankong_test.egg-info/top_level.txt