Metadata-Version: 2.1
Name: yuankong_test
Version: 0.1
Summary: 一个简短的描述
Author: ltq_yuankong
Author-email: 1539365976@qq.com
Classifier: Programming Language :: Python :: 3
Classifier: License :: OSI Approved :: MIT License
Classifier: Operating System :: OS Independent
License-File: LICENSE
